crypto_exchange_news/__init__.py
crypto_exchange_news/cli.py
crypto_exchange_news/items.py
crypto_exchange_news/middlewares.py
crypto_exchange_news/pipelines.py
crypto_exchange_news/settings.py
crypto_exchange_news/spiders/__init__.py
crypto_exchange_news/spiders/binance.py
crypto_exchange_news/spiders/bingx.py
crypto_exchange_news/spiders/bitfinex.py
crypto_exchange_news/spiders/bitget.py
crypto_exchange_news/spiders/bybit.py
crypto_exchange_news/spiders/cryptocom.py
crypto_exchange_news/spiders/deepcoin.py
crypto_exchange_news/spiders/kraken.py
crypto_exchange_news/spiders/kucoin.py
crypto_exchange_news/spiders/mexc.py
crypto_exchange_news/spiders/okx.py
crypto_exchange_news/spiders/upbit.py
crypto_exchange_news/spiders/xt.py
crypto_exchange_news_crawler-0.1.9.dist-info/METADATA
crypto_exchange_news_crawler-0.1.9.dist-info/WHEEL
crypto_exchange_news_crawler-0.1.9.dist-info/entry_points.txt
crypto_exchange_news_crawler-0.1.9.dist-info/top_level.txt
crypto_exchange_news_crawler-0.1.9.dist-info/RECORD
