Metadata-Version: 2.4
Name: crypto_exchange_news_crawler
Version: 0.1.9
Summary: Cryptocurrency exchange announcement news crawler for major crypto exchanges
Home-page: https://github.com/lowweihong/crypto_exchange_news_crawler
Author: lowweihong
Author-email: lowweihong14@gmail.com
Project-URL: Bug Reports, https://github.com/lowweihong/crypto-exchange-news-crawler/issues
Project-URL: Source, https://github.com/lowweihong/crypto-exchange-news-crawler
Project-URL: Documentation, https://github.com/lowweihong/crypto-exchange-news-crawler#readme
Keywords: cryptocurrency,crypto,exchange,news,crawler,scraper,bybit,binance,bitget,bitfinex,xt,okx,bingx,kraken,crypto.com,mexc,deepcoin,kucoin,upbit,announcement,trading,bot,api,scrapy,web-scraping,fintech,blockchain,defi,trading-bot,crypto-news
Classifier: Development Status :: 4 - Beta
Classifier: Intended Audience :: Developers
Classifier: License :: OSI Approved :: MIT License
Classifier: Operating System :: OS Independent
Classifier: Programming Language :: Python :: 3
Classifier: Programming Language :: Python :: 3.7
Classifier: Programming Language :: Python :: 3.8
Classifier: Programming Language :: Python :: 3.9
Classifier: Programming Language :: Python :: 3.10
Classifier: Programming Language :: Python :: 3.11
Classifier: Topic :: Software Development :: Libraries :: Python Modules
Classifier: Topic :: Internet :: WWW/HTTP :: Indexing/Search
Classifier: Topic :: Office/Business :: Financial
Requires-Python: >=3.7
Requires-Dist: Scrapy>=2.11.0
Requires-Dist: scrapy-playwright>=0.0.25
Requires-Dist: playwright>=1.40.0
Dynamic: author
Dynamic: author-email
Dynamic: classifier
Dynamic: description
Dynamic: description-content-type
Dynamic: home-page
Dynamic: keywords
Dynamic: project-url
Dynamic: requires-dist
Dynamic: requires-python
Dynamic: summary
